vectordb_orm/__init__.py
vectordb_orm/attributes.py
vectordb_orm/backends/__init__.py
vectordb_orm/backends/base.py
vectordb_orm/backends/milvus/__init__.py
vectordb_orm/backends/milvus/indexes.py
vectordb_orm/backends/milvus/milvus.py
vectordb_orm/backends/milvus/similarity.py
vectordb_orm/backends/pinecone/__init__.py
vectordb_orm/backends/pinecone/indexes.py
vectordb_orm/backends/pinecone/pinecone.py
vectordb_orm/base.py
vectordb_orm/enums.py
vectordb_orm/fields.py
vectordb_orm/index.py
vectordb_orm/query.py
vectordb_orm/results.py
vectordb_orm/session.py
vectordb_orm/tests/__init__.py
vectordb_orm/tests/conftest.py
vectordb_orm/tests/milvus/__init__.py
vectordb_orm/tests/milvus/test_indexes.py
vectordb_orm/tests/milvus/test_milvus.py
vectordb_orm/tests/models.py
vectordb_orm/tests/test_base.py
vectordb_orm/tests/test_query.py
vectordb_orm-0.2.1.dist-info/LICENSE
vectordb_orm-0.2.1.dist-info/METADATA
vectordb_orm-0.2.1.dist-info/WHEEL
vectordb_orm-0.2.1.dist-info/RECORD
