Metadata-Version: 2.1
Name: vectordb-orm
Version: 0.2.1
Summary: 
Author: Pierce Freeman
Author-email: pierce@freeman.vc
Requires-Python: >=3.10,<4.0
Classifier: Programming Language :: Python :: 3
Classifier: Programming Language :: Python :: 3.10
Classifier: Programming Language :: Python :: 3.11
Requires-Dist: numpy (>=1.24.2,<2.0.0)
Requires-Dist: pinecone-client (>=2.2.1,<3.0.0)
Requires-Dist: protobuf (>=4.22.3,<5.0.0)
Requires-Dist: pymilvus (>=2.2.6,<3.0.0)
Requires-Dist: tqdm (>=4.65.0,<5.0.0)
